<?xml version="1.0" encoding="utf-8" ?>
<odoo>
    <record id="crm_case_form_view_oppor" model="ir.ui.view">
        <field name="name">crm.lead.form.opportunity.funnel.type</field>
        <field name="model">crm.lead</field>
        <field name="inherit_id" ref="crm.crm_case_form_view_oppor" />
        <field name="arch" type="xml">
            <xpath expr="//field[@name='user_id']" position="after">
                <field
                    name="funnel_type_id"
                    groups="crm_lead_funnel_type.crm_funnel_type_setting_group"
                />
            </xpath>
        </field>
    </record>
</odoo>
